{"missions":[{"id":"Prologue","name":"Prologue","bosses":[],"difficulties":[{"id":0,"isAdvanced":false,"isHardcore":false,"ratings":[{"rating":"Bronze","score":0},{"rating":"Silver","score":10000},{"rating":"Gold","score":13000},{"rating":"Diamond","score":15000}]},{"id":1,"isAdvanced":false,"isHardcore":true,"ratings":[{"rating":"Bronze","score":0},{"rating":"Silver","score":10000},{"rating":"Gold","score":13000},{"rating":"Diamond","score":15000}]},{"id":2,"isAdvanced":true,"isHardcore":false,"ratings":[{"rating":"Bronze","score":0},{"rating":"Silver","score":10000},{"rating":"Gold","score":13000},{"rating":"Diamond","score":15000}]},{"id":3,"isAdvanced":true,"isHardcore":true,"ratings":[{"rating":"Bronze","score":0},{"rating":"Silver","score":10000},{"rating":"Gold","score":13000},{"rating":"Diamond","score":15000}]}]},{"id":"Caverns","name":"The Algorithm","bosses":[2245910325,3890677524,1839017484,3348317660],"difficulties":[{"id":0,"isAdvanced":false,"isHardcore":false,"ratings":[{"rating":"Bronze","score":0},{"rating":"Silver","score":40000},{"rating":"Gold","score":49000},{"rating":"Diamond","score":64000}]},{"id":1,"isAdvanced":false,"isHardcore":true,"ratings":[{"rating":"Bronze","score":0},{"rating":"Silver","score":40000},{"rating":"Gold","score":49000},{"rating":"Diamond","score":64000}]},{"id":2,"isAdvanced":true,"isHardcore":false,"ratings":[{"rating":"Bronze","score":0},{"rating":"Silver","score":40000},{"rating":"Gold","score":49000},{"rating":"Diamond","score":64000}]},{"id":3,"isAdvanced":true,"isHardcore":true,"ratings":[{"rating":"Bronze","score":0},{"rating":"Silver","score":40000},{"rating":"Gold","score":49000},{"rating":"Diamond","score":64000}]}]},{"id":"Portal","name":"Void's Edge","bosses":[1494679148,1161440162],"difficulties":[{"id":0,"isAdvanced":false,"isHardcore":false,"ratings":[{"rating":"Bronze","score":0},{"rating":"Silver","score":62000},{"rating":"Gold","score":71000},{"rating":"Diamond","score":87000}]},{"id":1,"isAdvanced":false,"isHardcore":true,"ratings":[{"rating":"Bronze","score":0},{"rating":"Silver","score":62000},{"rating":"Gold","score":71000},{"rating":"Diamond","score":87000}]},{"id":2,"isAdvanced":true,"isHardcore":false,"ratings":[{"rating":"Bronze","score":0},{"rating":"Silver","score":62000},{"rating":"Gold","score":71000},{"rating":"Diamond","score":87000}]},{"id":3,"isAdvanced":true,"isHardcore":true,"ratings":[{"rating":"Bronze","score":0},{"rating":"Silver","score":62000},{"rating":"Gold","score":71000},{"rating":"Diamond","score":87000}]}]},{"id":"Captains","name":"The Renegade","bosses":[597984049],"difficulties":[{"id":0,"isAdvanced":false,"isHardcore":false,"ratings":[{"rating":"Bronze","score":0},{"rating":"Silver","score":49000},{"rating":"Gold","score":56000},{"rating":"Diamond","score":66000}]},{"id":1,"isAdvanced":false,"isHardcore":true,"ratings":[{"rating":"Bronze","score":0},{"rating":"Silver","score":49000},{"rating":"Gold","score":56000},{"rating":"Diamond","score":66000}]},{"id":2,"isAdvanced":true,"isHardcore":false,"ratings":[{"rating":"Bronze","score":0},{"rating":"Silver","score":49000},{"rating":"Gold","score":56000},{"rating":"Diamond","score":66000}]},{"id":3,"isAdvanced":true,"isHardcore":true,"ratings":[{"rating":"Bronze","score":0},{"rating":"Silver","score":49000},{"rating":"Gold","score":56000},{"rating":"Diamond","score":66000}]}]},{"id":"Evacuation","name":"The Archive","bosses":[2035557110],"difficulties":[{"id":0,"isAdvanced":false,"isHardcore":false,"ratings":[{"rating":"Bronze","score":0},{"rating":"Silver","score":35000},{"rating":"Gold","score":40000},{"rating":"Diamond","score":48000}]},{"id":1,"isAdvanced":false,"isHardcore":true,"ratings":[{"rating":"Bronze","score":0},{"rating":"Silver","score":35000},{"rating":"Gold","score":40000},{"rating":"Diamond","score":48000}]},{"id":2,"isAdvanced":true,"isHardcore":false,"ratings":[{"rating":"Bronze","score":0},{"rating":"Silver","score":35000},{"rating":"Gold","score":40000},{"rating":"Diamond","score":48000}]},{"id":3,"isAdvanced":true,"isHardcore":true,"ratings":[{"rating":"Bronze","score":0},{"rating":"Silver","score":35000},{"rating":"Gold","score":40000},{"rating":"Diamond","score":48000}]}]},{"id":"Ruins","name":"The Sentinel","bosses":[2009836121,218888505,3772237962],"difficulties":[{"id":0,"isAdvanced":false,"isHardcore":false,"ratings":[{"rating":"Bronze","score":0},{"rating":"Silver","score":48000},{"rating":"Gold","score":57000},{"rating":"Diamond","score":66000}]},{"id":1,"isAdvanced":false,"isHardcore":true,"ratings":[{"rating":"Bronze","score":0},{"rating":"Silver","score":48000},{"rating":"Gold","score":57000},{"rating":"Diamond","score":66000}]},{"id":2,"isAdvanced":true,"isHardcore":false,"ratings":[{"rating":"Bronze","score":0},{"rating":"Silver","score":48000},{"rating":"Gold","score":57000},{"rating":"Diamond","score":66000}]},{"id":3,"isAdvanced":true,"isHardcore":true,"ratings":[{"rating":"Bronze","score":0},{"rating":"Silver","score":48000},{"rating":"Gold","score":57000},{"rating":"Diamond","score":66000}]}]},{"id":"Observatory","name":"The Experiment","bosses":[3714287806,770710137],"difficulties":[{"id":0,"isAdvanced":false,"isHardcore":false,"ratings":[{"rating":"Bronze","score":0},{"rating":"Silver","score":43000},{"rating":"Gold","score":51000},{"rating":"Diamond","score":62000}]},{"id":1,"isAdvanced":false,"isHardcore":true,"ratings":[{"rating":"Bronze","score":0},{"rating":"Silver","score":43000},{"rating":"Gold","score":51000},{"rating":"Diamond","score":62000}]},{"id":2,"isAdvanced":true,"isHardcore":false,"ratings":[{"rating":"Bronze","score":0},{"rating":"Silver","score":43000},{"rating":"Gold","score":51000},{"rating":"Diamond","score":62000}]},{"id":3,"isAdvanced":true,"isHardcore":true,"ratings":[{"rating":"Bronze","score":0},{"rating":"Silver","score":43000},{"rating":"Gold","score":51000},{"rating":"Diamond","score":62000}]}]},{"id":"Refinery","name":"The Saboteur","bosses":[3405178266,1522010304,1193142349],"difficulties":[{"id":0,"isAdvanced":false,"isHardcore":false,"ratings":[{"rating":"Bronze","score":0},{"rating":"Silver","score":50000},{"rating":"Gold","score":56000},{"rating":"Diamond","score":66000}]},{"id":1,"isAdvanced":false,"isHardcore":true,"ratings":[{"rating":"Bronze","score":0},{"rating":"Silver","score":50000},{"rating":"Gold","score":56000},{"rating":"Diamond","score":66000}]},{"id":2,"isAdvanced":true,"isHardcore":false,"ratings":[{"rating":"Bronze","score":0},{"rating":"Silver","score":50000},{"rating":"Gold","score":56000},{"rating":"Diamond","score":66000}]},{"id":3,"isAdvanced":true,"isHardcore":true,"ratings":[{"rating":"Bronze","score":0},{"rating":"Silver","score":50000},{"rating":"Gold","score":56000},{"rating":"Diamond","score":66000}]}]},{"id":"Cathedral","name":"The Heliophage","bosses":[476085965],"difficulties":[{"id":0,"isAdvanced":false,"isHardcore":false,"ratings":[{"rating":"Bronze","score":0},{"rating":"Silver","score":46000},{"rating":"Gold","score":62000},{"rating":"Diamond","score":89000}]},{"id":1,"isAdvanced":false,"isHardcore":true,"ratings":[{"rating":"Bronze","score":0},{"rating":"Silver","score":46000},{"rating":"Gold","score":62000},{"rating":"Diamond","score":89000}]},{"id":2,"isAdvanced":true,"isHardcore":false,"ratings":[{"rating":"Bronze","score":0},{"rating":"Silver","score":46000},{"rating":"Gold","score":62000},{"rating":"Diamond","score":89000}]},{"id":3,"isAdvanced":true,"isHardcore":true,"ratings":[{"rating":"Bronze","score":0},{"rating":"Silver","score":46000},{"rating":"Gold","score":62000},{"rating":"Diamond","score":89000}]}]},{"id":"Slums","name":"Attikus and the Thrall Rebellion","bosses":[749681276],"dlc":true,"difficulties":[{"id":0,"isAdvanced":false,"isHardcore":false,"ratings":[{"rating":"Bronze","score":0},{"rating":"Silver","score":69000},{"rating":"Gold","score":78000},{"rating":"Diamond","score":92000}]},{"id":1,"isAdvanced":false,"isHardcore":true,"ratings":[{"rating":"Bronze","score":0},{"rating":"Silver","score":69000},{"rating":"Gold","score":78000},{"rating":"Diamond","score":92000}]},{"id":2,"isAdvanced":true,"isHardcore":false,"ratings":[{"rating":"Bronze","score":0},{"rating":"Silver","score":69000},{"rating":"Gold","score":78000},{"rating":"Diamond","score":92000}]},{"id":3,"isAdvanced":true,"isHardcore":true,"ratings":[{"rating":"Bronze","score":0},{"rating":"Silver","score":69000},{"rating":"Gold","score":78000},{"rating":"Diamond","score":92000}]}]},{"id":"Toby_Raid","name":"Toby's Friendship Raid","bosses":[1224357252],"dlc":true,"difficulties":[{"id":0,"isAdvanced":false,"isHardcore":false,"ratings":[{"rating":"Bronze","score":0},{"rating":"Silver","score":35000},{"rating":"Gold","score":46000},{"rating":"Diamond","score":9999999}]},{"id":1,"isAdvanced":false,"isHardcore":true,"ratings":[{"rating":"Bronze","score":0},{"rating":"Silver","score":35000},{"rating":"Gold","score":46000},{"rating":"Diamond","score":9999999}]},{"id":2,"isAdvanced":true,"isHardcore":false,"ratings":[{"rating":"Bronze","score":0},{"rating":"Silver","score":46000},{"rating":"Gold","score":57000},{"rating":"Diamond","score":9999999}]},{"id":3,"isAdvanced":true,"isHardcore":true,"ratings":[{"rating":"Bronze","score":0},{"rating":"Silver","score":46000},{"rating":"Gold","score":57000},{"rating":"Diamond","score":9999999}]}]},{"id":"BattleSchool","name":"Oscar Mike vs The Battle School","bosses":[2663302101,343024219,3429178011,1819612576],"dlc":true,"difficulties":[{"id":0,"isAdvanced":false,"isHardcore":false,"ratings":[{"rating":"Bronze","score":0},{"rating":"Silver","score":70000},{"rating":"Gold","score":110000},{"rating":"Diamond","score":135000}]},{"id":1,"isAdvanced":false,"isHardcore":true,"ratings":[{"rating":"Bronze","score":0},{"rating":"Silver","score":70000},{"rating":"Gold","score":100000},{"rating":"Diamond","score":130000}]},{"id":2,"isAdvanced":true,"isHardcore":false,"ratings":[{"rating":"Bronze","score":0},{"rating":"Silver","score":70000},{"rating":"Gold","score":110000},{"rating":"Diamond","score":135000}]},{"id":3,"isAdvanced":true,"isHardcore":true,"ratings":[{"rating":"Bronze","score":0},{"rating":"Silver","score":70000},{"rating":"Gold","score":110000},{"rating":"Diamond","score":135000}]}]},{"id":"TallTales","name":"Montana and the Demon Bear","bosses":[2365742955],"dlc":true,"difficulties":[{"id":0,"isAdvanced":false,"isHardcore":false,"ratings":[{"rating":"Bronze","score":0},{"rating":"Silver","score":60000},{"rating":"Gold","score":90000},{"rating":"Diamond","score":110000}]},{"id":1,"isAdvanced":false,"isHardcore":true,"ratings":[{"rating":"Bronze","score":0},{"rating":"Silver","score":60000},{"rating":"Gold","score":90000},{"rating":"Diamond","score":110000}]},{"id":2,"isAdvanced":true,"isHardcore":false,"ratings":[{"rating":"Bronze","score":0},{"rating":"Silver","score":60000},{"rating":"Gold","score":90000},{"rating":"Diamond","score":110000}]},{"id":3,"isAdvanced":true,"isHardcore":true,"ratings":[{"rating":"Bronze","score":0},{"rating":"Silver","score":60000},{"rating":"Gold","score":90000},{"rating":"Diamond","score":110000}]}]}]}